bokcolmaps/CMSlicer.py
bokcolmaps/CMSlicer2D.py
bokcolmaps/CMSlicer3D.py
bokcolmaps/ColourMap.py
bokcolmaps/ColourMapLP.py
bokcolmaps/ColourMapLPSlider.py
bokcolmaps/ColourMapSlider.py
bokcolmaps/SpotPlot.py
bokcolmaps/SpotPlotLP.py
bokcolmaps/SpotPlotLPSlider.py
bokcolmaps/SpotPlotSlider.py
bokcolmaps/__init__.py
bokcolmaps/check_kwargs.py
bokcolmaps/generate_colourbar.py
bokcolmaps/get_common_kwargs.py
bokcolmaps/get_min_max.py
bokcolmaps/jet.txt
bokcolmaps/plot_colourmap.py
bokcolmaps/read_colourmap.py
bokcolmaps/Examples/CMSlicerExample2D.py
bokcolmaps/Examples/CMSlicerExample3D.py
bokcolmaps/Examples/ColourMapExample.html
bokcolmaps/Examples/ColourMapExample.py
bokcolmaps/Examples/ColourMapLPSliderExample.html
bokcolmaps/Examples/ColourMapLPSliderExample.py
bokcolmaps/Examples/ColourMapLPSliderServerExample.py
bokcolmaps/Examples/SpotPlotExample.html
bokcolmaps/Examples/SpotPlotExample.py
bokcolmaps/Examples/SpotPlotLPSliderExample.py
bokcolmaps/Examples/__init__.py
bokcolmaps/Examples/colourmap.html
bokcolmaps/Examples/colourmap3D.html
bokcolmaps/Examples/example_data.py
bokcolmaps/Examples/plot_colourmap_example.py
bokcolmaps-4.4.0.dist-info/licenses/LICENSE.md
bokcolmaps-4.4.0.dist-info/METADATA
bokcolmaps-4.4.0.dist-info/WHEEL
bokcolmaps-4.4.0.dist-info/top_level.txt
bokcolmaps-4.4.0.dist-info/RECORD
